blocks_genesis/__init__.py
blocks_genesis/_auth/__init__.py
blocks_genesis/_auth/auth.py
blocks_genesis/_auth/blocks_context.py
blocks_genesis/_cache/CacheClient.py
blocks_genesis/_cache/__init__.py
blocks_genesis/_cache/cache_provider.py
blocks_genesis/_cache/redis_client.py
blocks_genesis/_core/__init__.py
blocks_genesis/_core/api.py
blocks_genesis/_core/azure_key_vault.py
blocks_genesis/_core/blocks_secret.py
blocks_genesis/_core/change_context.py
blocks_genesis/_core/configuration.py
blocks_genesis/_core/env_vault_config.py
blocks_genesis/_core/secret_loader.py
blocks_genesis/_core/worker.py
blocks_genesis/_database/__init__.py
blocks_genesis/_database/db_context.py
blocks_genesis/_database/mongo_context.py
blocks_genesis/_database/mongo_event_subscriber.py
blocks_genesis/_entities/__init__.py
blocks_genesis/_entities/base_entity.py
blocks_genesis/_lmt/__init__.py
blocks_genesis/_lmt/activity.py
blocks_genesis/_lmt/log_config.py
blocks_genesis/_lmt/mongo_log_exporter.py
blocks_genesis/_lmt/mongo_trace_exporter.py
blocks_genesis/_lmt/tracing.py
blocks_genesis/_message/__init__.py
blocks_genesis/_message/consumer.py
blocks_genesis/_message/consumer_message.py
blocks_genesis/_message/event_message.py
blocks_genesis/_message/event_registry.py
blocks_genesis/_message/message_client.py
blocks_genesis/_message/message_configuration.py
blocks_genesis/_message/azure/azure_message_client.py
blocks_genesis/_message/azure/azure_message_worker.py
blocks_genesis/_message/azure/config_azure_service_bus.py
blocks_genesis/_middlewares/__init__.py
blocks_genesis/_middlewares/global_exception_middleware.py
blocks_genesis/_middlewares/tenant_middleware.py
blocks_genesis/_tenant/__init__.py
blocks_genesis/_tenant/tenant.py
blocks_genesis/_tenant/tenant_service.py
blocks_genesis/_utilities/__init__.py
blocks_genesis/_utilities/crypto_service.py
seliseblocks_genesis-0.2.24.dist-info/METADATA
seliseblocks_genesis-0.2.24.dist-info/WHEEL
seliseblocks_genesis-0.2.24.dist-info/licenses/LICENSE
seliseblocks_genesis-0.2.24.dist-info/RECORD
