Metadata-Version: 2.4
Name: seliseblocks-genesis
Version: 0.2.24
Summary: Reusable FastAPI utilities like middlewares, singletons, and more for Selise Blocks and Selise Genesis projects.
Project-URL: Homepage, https://github.com/SELISEdigitalplatforms/l0-py-blocks-genesis
Project-URL: Repository, https://github.com/SELISEdigitalplatforms/l0-py-blocks-genesis
Author-email: Selise Blocks <mostafizur.rahman@selisegroup.com>
License-File: LICENSE
Keywords: Blocks genesis,FastAPI,Middlewares,Selise,Selise Blocks,Selise genesis,Singletons
Requires-Python: >=3.9
Requires-Dist: aiohttp>=3.12.9
Requires-Dist: azure-identity>=1.7.0
Requires-Dist: azure-keyvault-secrets>=4.3.0
Requires-Dist: azure-servicebus>=7.14.2
Requires-Dist: cors>=1.0.1
Requires-Dist: fastapi>=0.68.0
Requires-Dist: motor>=2.5.0
Requires-Dist: opentelemetry-api>=1.33.1
Requires-Dist: opentelemetry-instrumentation-fastapi>=0.54b1
Requires-Dist: opentelemetry-instrumentation-redis>=0.54b1
Requires-Dist: opentelemetry-sdk>=1.33.1
Requires-Dist: pydantic>=2.11.5
Requires-Dist: pymongo>=4.13.0
Requires-Dist: python-dotenv>=0.19.0
Requires-Dist: redis>=4.0.0
Requires-Dist: structlog>=21.1.0
Requires-Dist: uvicorn>=0.15.0
